{
  "AOO": {
    "Lower_Rate_Limit": {
      "min": 30,
      "max": 175,
      "step": 5,
      "unit": "ppm",
      "default": 60,
      "data_type": "int",
      "packet_format": "H"
    },
    "Upper_Rate_Limit": {
      "min": 50,
      "max": 175,
      "step": 5,
      "unit": "ppm",
      "default": 120,
      "data_type": "int",
      "packet_format": "H"
    },
    "Atrial_Amplitude": {
      "min": 0.0,
      "max": 5.0,
      "step": 0.1,
      "unit": "V",
      "default": 5.0,
      "data_type": "float",
      "packet_format": "f"
    },
    "Atrial_Pulse_Width": {
      "min": 1,
      "max": 30,
      "step": 1,
      "unit": "ms",
      "default": 1,
      "data_type": "int",
      "packet_format": "H"
    }
  },
  "VOO": {
    "Lower_Rate_Limit": {
      "min": 30,
      "max": 175,
      "step": 5,
      "unit": "ppm",
      "default": 60,
      "data_type": "int",
      "packet_format": "H"
    },
    "Upper_Rate_Limit": {
      "min": 50,
      "max": 175,
      "step": 5,
      "unit": "ppm",
      "default": 120,
      "data_type": "int",
      "packet_format": "H"
    },
    "Ventricular_Amplitude": {
      "min": 0.0,
      "max": 5.0,
      "step": 0.1,
      "unit": "V",
      "default": 5.0,
      "data_type": "float",
      "packet_format": "f"
    },
    "Ventricular_Pulse_Width": {
      "min": 1,
      "max": 30,
      "step": 1,
      "unit": "ms",
      "default": 1,
      "data_type": "int",
      "packet_format": "H"
    }
  },
  "AAI": {
    "Lower_Rate_Limit": {
      "min": 30,
      "max": 175,
      "step": 5,
      "unit": "ppm",
      "default": 60,
      "data_type": "int",
      "packet_format": "H"
    },
    "Upper_Rate_Limit": {
      "min": 50,
      "max": 175,
      "step": 5,
      "unit": "ppm",
      "default": 120,
      "data_type": "int",
      "packet_format": "H"
    },
    "Atrial_Amplitude": {
      "min": 0.0,
      "max": 5.0,
      "step": 0.1,
      "unit": "V",
      "default": 5.0,
      "data_type": "float",
      "packet_format": "f"
    },
    "Atrial_Pulse_Width": {
      "min": 1,
      "max": 30,
      "step": 1,
      "unit": "ms",
      "default": 1,
      "data_type": "int",
      "packet_format": "H"
    },
    "Atrial_Sensitivity": {
      "min": 0.0,
      "max": 5.0,
      "step": 0.1,
      "unit": "V",
      "default": 0.75,
      "data_type": "float",
      "packet_format": "f"
    },
    "ARP": {
      "min": 150,
      "max": 500,
      "step": 10,
      "unit": "ms",
      "default": 250,
      "data_type": "int",
      "packet_format": "H"
    },
    "PVARP": {
      "min": 150,
      "max": 500,
      "step": 10,
      "unit": "ms",
      "default": 250,
      "data_type": "int",
      "packet_format": "H"
    },
    "Hysteresis": {
      "min": 0,
      "max": 175,
      "step": 5,
      "unit": "ppm",
      "default": 0,
      "data_type": "int",
      "packet_format": "H"
    },
    "Rate_Smoothing": {
      "min": 0,
      "max": 25,
      "step": 3,
      "unit": "%",
      "default": 0,
      "data_type": "int",
      "packet_format": "H"
    }
  },
  "VVI": {
    "Lower_Rate_Limit": {
      "min": 30,
      "max": 175,
      "step": 5,
      "unit": "ppm",
      "default": 60,
      "data_type": "int",
      "packet_format": "H"
    },
    "Upper_Rate_Limit": {
      "min": 50,
      "max": 175,
      "step": 5,
      "unit": "ppm",
      "default": 120,
      "data_type": "int",
      "packet_format": "H"
    },
    "Ventricular_Amplitude": {
      "min": 0.0,
      "max": 5.0,
      "step": 0.1,
      "unit": "V",
      "default": 5.0,
      "data_type": "float",
      "packet_format": "f"
    },
    "Ventricular_Pulse_Width": {
      "min": 1,
      "max": 30,
      "step": 1,
      "unit": "ms",
      "default": 1,
      "data_type": "int",
      "packet_format": "H"
    },
    "Ventricular_Sensitivity": {
      "min": 0.0,
      "max": 5.0,
      "step": 0.1,
      "unit": "V",
      "default": 2.5,
      "data_type": "float",
      "packet_format": "f"
    },
    "VRP": {
      "min": 150,
      "max": 500,
      "step": 10,
      "unit": "ms",
      "default": 320,
      "data_type": "int",
      "packet_format": "H"
    },
    "Hysteresis": {
      "min": 0,
      "max": 175,
      "step": 5,
      "unit": "ppm",
      "default": 0,
      "data_type": "int",
      "packet_format": "H"
    },
    "Rate_Smoothing": {
      "min": 0,
      "max": 25,
      "step": 3,
      "unit": "%",
      "default": 0,
      "data_type": "int",
      "packet_format": "H"
    }
  },
  "AOOR": {
    "Lower_Rate_Limit": {
      "min": 30,
      "max": 175,
      "step": 5,
      "unit": "ppm",
      "default": 60,
      "data_type": "int",
      "packet_format": "H"
    },
    "Upper_Rate_Limit": {
      "min": 50,
      "max": 175,
      "step": 5,
      "unit": "ppm",
      "default": 120,
      "data_type": "int",
      "packet_format": "H"
    },
    "Maximum_Sensor_Rate": {
      "min": 50,
      "max": 175,
      "step": 5,
      "unit": "ppm",
      "default": 120,
      "data_type": "int",
      "packet_format": "H"
    },
    "Atrial_Amplitude": {
      "min": 0.0,
      "max": 5.0,
      "step": 0.1,
      "unit": "V",
      "default": 5.0,
      "data_type": "float",
      "packet_format": "f"
    },
    "Atrial_Pulse_Width": {
      "min": 1,
      "max": 30,
      "step": 1,
      "unit": "ms",
      "default": 1,
      "data_type": "int",
      "packet_format": "H"
    },
    "Activity_Threshold": {
      "input_type": "enum",
      "options": [
        "V-Low",
        "Low",
        "Med-Low",
        "Med",
        "Med-High",
        "High",
        "V-High"
      ],
      "unit": "level",
      "default": "Med",
      "packet_format": "B"
    },
    "Reaction_Time": {
      "min": 10,
      "max": 50,
      "step": 10,
      "unit": "s",
      "default": 30,
      "data_type": "int",
      "packet_format": "H"
    },
    "Response_Factor": {
      "min": 1,
      "max": 16,
      "step": 1,
      "unit": "",
      "default": 8,
      "data_type": "int",
      "packet_format": "B"
    },
    "Recovery_Time": {
      "min": 2,
      "max": 16,
      "step": 1,
      "unit": "min",
      "default": 5,
      "data_type": "int",
      "packet_format": "B"
    }
  },
  "VOOR": {
    "Lower_Rate_Limit": {
      "min": 30,
      "max": 175,
      "step": 5,
      "unit": "ppm",
      "default": 60,
      "data_type": "int",
      "packet_format": "H"
    },
    "Upper_Rate_Limit": {
      "min": 50,
      "max": 175,
      "step": 5,
      "unit": "ppm",
      "default": 120,
      "data_type": "int",
      "packet_format": "H"
    },
    "Maximum_Sensor_Rate": {
      "min": 50,
      "max": 175,
      "step": 5,
      "unit": "ppm",
      "default": 120,
      "data_type": "int",
      "packet_format": "H"
    },
    "Ventricular_Amplitude": {
      "min": 0.0,
      "max": 5.0,
      "step": 0.1,
      "unit": "V",
      "default": 5.0,
      "data_type": "float",
      "packet_format": "f"
    },
    "Ventricular_Pulse_Width": {
      "min": 1,
      "max": 30,
      "step": 1,
      "unit": "ms",
      "default": 1,
      "data_type": "int",
      "packet_format": "H"
    },
    "Activity_Threshold": {
      "input_type": "enum",
      "options": [
        "V-Low",
        "Low",
        "Med-Low",
        "Med",
        "Med-High",
        "High",
        "V-High"
      ],
      "unit": "level",
      "default": "Med",
      "packet_format": "B"
    },
    "Reaction_Time": {
      "min": 10,
      "max": 50,
      "step": 10,
      "unit": "s",
      "default": 30,
      "data_type": "int",
      "packet_format": "H"
    },
    "Response_Factor": {
      "min": 1,
      "max": 16,
      "step": 1,
      "unit": "",
      "default": 8,
      "data_type": "int",
      "packet_format": "B"
    },
    "Recovery_Time": {
      "min": 2,
      "max": 16,
      "step": 1,
      "unit": "min",
      "default": 5,
      "data_type": "int",
      "packet_format": "B"
    }
  },
  "AAIR": {
    "Lower_Rate_Limit": {
      "min": 30,
      "max": 175,
      "step": 5,
      "unit": "ppm",
      "default": 60,
      "data_type": "int",
      "packet_format": "H"
    },
    "Upper_Rate_Limit": {
      "min": 50,
      "max": 175,
      "step": 5,
      "unit": "ppm",
      "default": 120,
      "data_type": "int",
      "packet_format": "H"
    },
    "Maximum_Sensor_Rate": {
      "min": 50,
      "max": 175,
      "step": 5,
      "unit": "ppm",
      "default": 120,
      "data_type": "int",
      "packet_format": "H"
    },
    "Atrial_Amplitude": {
      "min": 0.0,
      "max": 5.0,
      "step": 0.1,
      "unit": "V",
      "default": 5.0,
      "data_type": "float",
      "packet_format": "f"
    },
    "Atrial_Pulse_Width": {
      "min": 1,
      "max": 30,
      "step": 1,
      "unit": "ms",
      "default": 1,
      "data_type": "int",
      "packet_format": "H"
    },
    "Atrial_Sensitivity": {
      "min": 0.0,
      "max": 5.0,
      "step": 0.1,
      "unit": "V",
      "default": 0.75,
      "data_type": "float",
      "packet_format": "f"
    },
    "ARP": {
      "min": 150,
      "max": 500,
      "step": 10,
      "unit": "ms",
      "default": 250,
      "data_type": "int",
      "packet_format": "H"
    },
    "PVARP": {
      "min": 150,
      "max": 500,
      "step": 10,
      "unit": "ms",
      "default": 250,
      "data_type": "int",
      "packet_format": "H"
    },
    "Hysteresis": {
      "min": 0,
      "max": 175,
      "step": 5,
      "unit": "ppm",
      "default": 0,
      "data_type": "int",
      "packet_format": "H"
    },
    "Rate_Smoothing": {
      "min": 0,
      "max": 25,
      "step": 3,
      "unit": "%",
      "default": 0,
      "data_type": "int",
      "packet_format": "H"
    },
    "Activity_Threshold": {
      "input_type": "enum",
      "options": [
        "V-Low",
        "Low",
        "Med-Low",
        "Med",
        "Med-High",
        "High",
        "V-High"
      ],
      "unit": "level",
      "default": "Med",
      "packet_format": "B"
    },
    "Reaction_Time": {
      "min": 10,
      "max": 50,
      "step": 10,
      "unit": "s",
      "default": 30,
      "data_type": "int",
      "packet_format": "H"
    },
    "Response_Factor": {
      "min": 1,
      "max": 16,
      "step": 1,
      "unit": "",
      "default": 8,
      "data_type": "int",
      "packet_format": "B"
    },
    "Recovery_Time": {
      "min": 2,
      "max": 16,
      "step": 1,
      "unit": "min",
      "default": 5,
      "data_type": "int",
      "packet_format": "B"
    }
  },
  "VVIR": {
    "Lower_Rate_Limit": {
      "min": 30,
      "max": 175,
      "step": 5,
      "unit": "ppm",
      "default": 60,
      "data_type": "int",
      "packet_format": "H"
    },
    "Upper_Rate_Limit": {
      "min": 50,
      "max": 175,
      "step": 5,
      "unit": "ppm",
      "default": 120,
      "data_type": "int",
      "packet_format": "H"
    },
    "Maximum_Sensor_Rate": {
      "min": 50,
      "max": 175,
      "step": 5,
      "unit": "ppm",
      "default": 120,
      "data_type": "int",
      "packet_format": "H"
    },
    "Ventricular_Amplitude": {
      "min": 0.0,
      "max": 5.0,
      "step": 0.1,
      "unit": "V",
      "default": 5.0,
      "data_type": "float",
      "packet_format": "f"
    },
    "Ventricular_Pulse_Width": {
      "min": 1,
      "max": 30,
      "step": 1,
      "unit": "ms",
      "default": 1,
      "data_type": "int",
      "packet_format": "H"
    },
    "Ventricular_Sensitivity": {
      "min": 0.0,
      "max": 5.0,
      "step": 0.1,
      "unit": "V",
      "default": 2.5,
      "data_type": "float",
      "packet_format": "f"
    },
    "VRP": {
      "min": 150,
      "max": 500,
      "step": 10,
      "unit": "ms",
      "default": 320,
      "data_type": "int",
      "packet_format": "H"
    },
    "Hysteresis": {
      "min": 0,
      "max": 175,
      "step": 5,
      "unit": "ppm",
      "default": 0,
      "data_type": "int",
      "packet_format": "H"
    },
    "Rate_Smoothing": {
      "min": 0,
      "max": 25,
      "step": 3,
      "unit": "%",
      "default": 0,
      "data_type": "int",
      "packet_format": "H"
    },
    "Activity_Threshold": {
      "input_type": "enum",
      "options": [
        "V-Low",
        "Low",
        "Med-Low",
        "Med",
        "Med-High",
        "High",
        "V-High"
      ],
      "unit": "level",
      "default": "Med",
      "packet_format": "B"
    },
    "Reaction_Time": {
      "min": 10,
      "max": 50,
      "step": 10,
      "unit": "s",
      "default": 30,
      "data_type": "int",
      "packet_format": "H"
    },
    "Response_Factor": {
      "min": 1,
      "max": 16,
      "step": 1,
      "unit": "",
      "default": 8,
      "data_type": "int",
      "packet_format": "B"
    },
    "Recovery_Time": {
      "min": 2,
      "max": 16,
      "step": 1,
      "unit": "min",
      "default": 5,
      "data_type": "int",
      "packet_format": "B"
    }
  },
  "DDDR": {
    "Lower_Rate_Limit": {
      "min": 30,
      "max": 175,
      "step": 5,
      "unit": "ppm",
      "default": 60,
      "data_type": "int",
      "packet_format": "H"
    },
    "Upper_Rate_Limit": {
      "min": 50,
      "max": 175,
      "step": 5,
      "unit": "ppm",
      "default": 120,
      "data_type": "int",
      "packet_format": "H"
    },
    "Maximum_Sensor_Rate": {
      "min": 50,
      "max": 175,
      "step": 5,
      "unit": "ppm",
      "default": 120,
      "data_type": "int",
      "packet_format": "H"
    },
    "Fixed_AV_Delay": {
      "min": 70,
      "max": 300,
      "step": 10,
      "unit": "ms",
      "default": 150,
      "data_type": "int",
      "packet_format": "H"
    },
    "Dynamic_AV_Delay": {
      "input_type": "enum",
      "options": ["Off", "On"],
      "unit": "",
      "default": "Off",
      "packet_format": "B"
    },
    "Sensed_AV_Delay_Offset": {
      "min": -100,
      "max": -10,
      "step": 10,
      "unit": "ms",
      "default": -10,
      "data_type": "int",
      "packet_format": "H"
    },
    "Atrial_Amplitude": {
      "min": 0.0,
      "max": 5.0,
      "step": 0.1,
      "unit": "V",
      "default": 5.0,
      "data_type": "float",
      "packet_format": "f"
    },
    "Ventricular_Amplitude": {
      "min": 0.0,
      "max": 5.0,
      "step": 0.1,
      "unit": "V",
      "default": 5.0,
      "data_type": "float",
      "packet_format": "f"
    },
    "Atrial_Pulse_Width": {
      "min": 1,
      "max": 30,
      "step": 1,
      "unit": "ms",
      "default": 1,
      "data_type": "int",
      "packet_format": "H"
    },
    "Ventricular_Pulse_Width": {
      "min": 1,
      "max": 30,
      "step": 1,
      "unit": "ms",
      "default": 1,
      "data_type": "int",
      "packet_format": "H"
    },
    "Atrial_Sensitivity": {
      "min": 0.0,
      "max": 5.0,
      "step": 0.1,
      "unit": "V",
      "default": 0.75,
      "data_type": "float",
      "packet_format": "f"
    },
    "Ventricular_Sensitivity": {
      "min": 0.0,
      "max": 5.0,
      "step": 0.1,
      "unit": "V",
      "default": 2.5,
      "data_type": "float",
      "packet_format": "f"
    },
    "VRP": {
      "min": 150,
      "max": 500,
      "step": 10,
      "unit": "ms",
      "default": 320,
      "data_type": "int",
      "packet_format": "H"
    },
    "ARP": {
      "min": 150,
      "max": 500,
      "step": 10,
      "unit": "ms",
      "default": 250,
      "data_type": "int",
      "packet_format": "H"
    },
    "PVARP": {
      "min": 150,
      "max": 500,
      "step": 10,
      "unit": "ms",
      "default": 250,
      "data_type": "int",
      "packet_format": "H"
    },
    "PVARP_Extension": {
      "min": 50,
      "max": 400,
      "step": 50,
      "unit": "ms",
      "default": 50,
      "data_type": "int",
      "packet_format": "H"
    },
    "Hysteresis": {
      "min": 0,
      "max": 175,
      "step": 5,
      "unit": "ppm",
      "default": 0,
      "data_type": "int",
      "packet_format": "H"
    },
    "Rate_Smoothing": {
      "min": 0,
      "max": 25,
      "step": 3,
      "unit": "%",
      "default": 0,
      "data_type": "int",
      "packet_format": "H"
    },
    "Activity_Threshold": {
      "input_type": "enum",
      "options": [
        "V-Low",
        "Low",
        "Med-Low",
        "Med",
        "Med-High",
        "High",
        "V-High"
      ],
      "unit": "level",
      "default": "Med",
      "packet_format": "B"
    },
    "Reaction_Time": {
      "min": 10,
      "max": 50,
      "step": 10,
      "unit": "s",
      "default": 30,
      "data_type": "int",
      "packet_format": "H"
    },
    "Response_Factor": {
      "min": 1,
      "max": 16,
      "step": 1,
      "unit": "",
      "default": 8,
      "data_type": "int",
      "packet_format": "B"
    },
    "Recovery_Time": {
      "min": 2,
      "max": 16,
      "step": 1,
      "unit": "min",
      "default": 5,
      "data_type": "int",
      "packet_format": "B"
    }
  }
}
